MANIFEST.in
README.rst
requirements.txt
setup.cfg
setup.py
tests/__init__.py
tests/test_handler.py
tests/util.py
tests/cache/__init__.py
tests/cache/test_util.py
tests/controller/__init__.py
tests/controller/test_base.py
tests/core/__init__.py
tests/core/test_dispatcher.py
tests/core/test_meta.py
tests/core/test_server.py
torneira/__init__.py
torneira/handler.py
torneira.egg-info/PKG-INFO
torneira.egg-info/SOURCES.txt
torneira.egg-info/dependency_links.txt
torneira.egg-info/entry_points.txt
torneira.egg-info/requires.txt
torneira.egg-info/top_level.txt
torneira/cache/__init__.py
torneira/cache/backend.py
torneira/cache/extension.py
torneira/cache/util.py
torneira/controller/__init__.py
torneira/controller/base.py
torneira/core/__init__.py
torneira/core/dispatcher.py
torneira/core/meta.py
torneira/core/server.py
torneira/helper/__init__.py
torneira/helper/encoding.py
torneira/models/__init__.py
torneira/models/base.py
torneira/runner/__init__.py
torneira/runner/cli.py
torneira/runner/main.py
torneira/template/__init__.py
torneira/template/mako_engine.py
torneira/testing/__init__.py
torneira/testing/client.py
torneira/testing/testcase.py