Metadata-Version: 1.0
Name: torneira
Version: 0.3.3
Summary: Torneira is a lightweight web framework build on top of Tornado
Home-page: http://github.com/marcelnicolay/torneira
Author: Marcel Nicolay
Author-email: marcel.nicolay@gmail.com
License: OSI
Keywords: torneira,tornado
Platform: UNKNOWN
